dfl/__init__.py
dfl/dfl.py
pydfl-0.1.0.dist-info/WHEEL
pydfl-0.1.0.dist-info/METADATA
pydfl-0.1.0.dist-info/RECORD
