Metadata-Version: 2.1
Name: pydfl
Version: 0.1.0
Summary: Toolsets for transforming and searching the path of dfl(Directory, File, Link)
Author: Doohoon Kim
Author-email: me@doohoon.kim
Requires-Python: >=3.10,<4.0
Classifier: Programming Language :: Python :: 3
Classifier: Programming Language :: Python :: 3.10
Classifier: Programming Language :: Python :: 3.11
